ipywidgethello/__init__.py
ipywidgethello/_version.py
ipywidgethello/example.py
ipywidgethello/labextension/jupyter-widget-hello-0.2.3.tgz
ipywidgethello/nbextension/__init__.py
ipywidgethello/nbextension/static/extension.js
ipywidgethello/nbextension/static/index.js
ipywidgethello/nbextension/static/index.js.map
ipywidgethello/tests/__init__.py
ipywidgethello/tests/conftest.py
ipywidgethello/tests/test_example.py
ipywidgethello/tests/test_nbextension_path.py
ipywidgethello-0.2.3.data/data/etc/jupyter/nbconfig/notebook.d/jupyter-widget-hello.json
ipywidgethello-0.2.3.data/data/share/jupyter/lab/extensions/jupyter-widget-hello-0.2.3.tgz
ipywidgethello-0.2.3.data/data/share/jupyter/nbextensions/jupyter-widget-hello/extension.js
ipywidgethello-0.2.3.data/data/share/jupyter/nbextensions/jupyter-widget-hello/index.js
ipywidgethello-0.2.3.data/data/share/jupyter/nbextensions/jupyter-widget-hello/index.js.map
ipywidgethello-0.2.3.dist-info/DESCRIPTION.rst
ipywidgethello-0.2.3.dist-info/METADATA
ipywidgethello-0.2.3.dist-info/RECORD
ipywidgethello-0.2.3.dist-info/WHEEL
ipywidgethello-0.2.3.dist-info/metadata.json
ipywidgethello-0.2.3.dist-info/top_level.txt
