Metadata-Version: 2.0
Name: ipywidgethello
Version: 0.2.3
Summary: Hello world for widgets!
Home-page: https://github.com/vidartf/ipywidgethello
Author: Vidar Tonaas Fauske
Author-email: vidartf@gmail.com
License: BSD
Keywords: Jupyter,Widgets,IPython
Platform: Linux
Platform: Mac OS X
Platform: Windows
Classifier: Intended Audience :: Developers
Classifier: Intended Audience :: Science/Research
Classifier: License :: OSI Approved :: BSD License
Classifier: Programming Language :: Python
Classifier: Programming Language :: Python :: 3
Classifier: Programming Language :: Python :: 3.4
Classifier: Programming Language :: Python :: 3.5
Classifier: Programming Language :: Python :: 3.6
Classifier: Framework :: Jupyter
Requires-Dist: ipywidgets (>=7.0.0)
Provides-Extra: docs
Requires-Dist: jupyter-sphinx; extra == 'docs'
Requires-Dist: nbsphinx (>=0.2.13); extra == 'docs'
Requires-Dist: nbsphinx-link; extra == 'docs'
Requires-Dist: sphinx (>=1.5); extra == 'docs'
Provides-Extra: examples
Provides-Extra: test
Requires-Dist: nbval; extra == 'test'
Requires-Dist: pytest; extra == 'test'
Requires-Dist: pytest-cov; extra == 'test'
